llamacloud_mcp/__init__.py
llamacloud_mcp/main.py
iflow_mcp_run_llama_llamacloud_mcp-1.0.0.dist-info/METADATA
iflow_mcp_run_llama_llamacloud_mcp-1.0.0.dist-info/WHEEL
iflow_mcp_run_llama_llamacloud_mcp-1.0.0.dist-info/entry_points.txt
iflow_mcp_run_llama_llamacloud_mcp-1.0.0.dist-info/licenses/LICENSE
iflow_mcp_run_llama_llamacloud_mcp-1.0.0.dist-info/RECORD
