Metadata-Version: 2.4
Name: iflow-mcp_run-llama_llamacloud-mcp
Version: 1.0.0
Summary: Expose LlamaCloud services as MCP tools
Author-email: Tuana Celik <tuana@runllama.ai>, Laurie Voss <laurie@runllama.ai>, Logan Markewich <logan@runllama.ai>
License-Expression: MIT
License-File: LICENSE
Keywords: llama,llama-cloud,llama-cloud-services,llamacloud,mcp
Requires-Python: >=3.10
Requires-Dist: click
Requires-Dist: llama-cloud-services
Requires-Dist: llama-index-indices-managed-llama-cloud>=0.6.9
Requires-Dist: llama-index-tools-mcp>=0.1.0
Requires-Dist: mcp[cli]>=1.6.0
Requires-Dist: python-dotenv>=1.1.0
